setup.py
client/__init__.py
client/client.py
client/client/__init__.py
client/client/add_contact_dialog.py
client/client/database.py
client/client/delete_contact.py
client/client/main_window.py
client/client/main_window_conv.py
client/client/transport.py
client/client/user_name_dialog.py
client_chat_pyqt.egg-info/PKG-INFO
client_chat_pyqt.egg-info/SOURCES.txt
client_chat_pyqt.egg-info/dependency_links.txt
client_chat_pyqt.egg-info/requires.txt
client_chat_pyqt.egg-info/top_level.txt