Metadata-Version: 1.0
Name: client-chat-pyqt
Version: 0.2
Summary: Client packet
Home-page: UNKNOWN
Author: Ekaterina Kondratyeva
Author-email: kondraa@gmail.com
License: UNKNOWN
Platform: UNKNOWN
